tabular2mcap/__init__.py
tabular2mcap/mcap_converter.py
tabular2mcap/converter/__init__.py
tabular2mcap/converter/common.py
tabular2mcap/converter/functions.py
tabular2mcap/converter/json.py
tabular2mcap/converter/others.py
tabular2mcap/converter/protobuf.py
tabular2mcap/converter/ros2.py
tabular2mcap/external/update_foxglove_schema.py
tabular2mcap/external/foxglove-sdk/schemas/jsonschema/ArrowPrimitive.json
tabular2mcap/external/foxglove-sdk/schemas/jsonschema/CameraCalibration.json
tabular2mcap/external/foxglove-sdk/schemas/jsonschema/CircleAnnotation.json
tabular2mcap/external/foxglove-sdk/schemas/jsonschema/Color.json
tabular2mcap/external/foxglove-sdk/schemas/jsonschema/CompressedImage.json
tabular2mcap/external/foxglove-sdk/schemas/jsonschema/CompressedVideo.json
tabular2mcap/external/foxglove-sdk/schemas/jsonschema/CubePrimitive.json
tabular2mcap/external/foxglove-sdk/schemas/jsonschema/CylinderPrimitive.json
tabular2mcap/external/foxglove-sdk/schemas/jsonschema/Duration.json
tabular2mcap/external/foxglove-sdk/schemas/jsonschema/FrameTransform.json
tabular2mcap/external/foxglove-sdk/schemas/jsonschema/FrameTransforms.json
tabular2mcap/external/foxglove-sdk/schemas/jsonschema/GeoJSON.json
tabular2mcap/external/foxglove-sdk/schemas/jsonschema/Grid.json
tabular2mcap/external/foxglove-sdk/schemas/jsonschema/ImageAnnotations.json
tabular2mcap/external/foxglove-sdk/schemas/jsonschema/KeyValuePair.json
tabular2mcap/external/foxglove-sdk/schemas/jsonschema/LaserScan.json
tabular2mcap/external/foxglove-sdk/schemas/jsonschema/LinePrimitive.json
tabular2mcap/external/foxglove-sdk/schemas/jsonschema/LocationFix.json
tabular2mcap/external/foxglove-sdk/schemas/jsonschema/LocationFixes.json
tabular2mcap/external/foxglove-sdk/schemas/jsonschema/Log.json
tabular2mcap/external/foxglove-sdk/schemas/jsonschema/ModelPrimitive.json
tabular2mcap/external/foxglove-sdk/schemas/jsonschema/PackedElementField.json
tabular2mcap/external/foxglove-sdk/schemas/jsonschema/Point2.json
tabular2mcap-0.1.12.dist-info/licenses/LICENSE
tabular2mcap-0.1.12.dist-info/METADATA
tabular2mcap-0.1.12.dist-info/WHEEL
tabular2mcap-0.1.12.dist-info/entry_points.txt
tabular2mcap-0.1.12.dist-info/top_level.txt
tabular2mcap-0.1.12.dist-info/RECORD
