Metadata-Version: 2.4
Name: tabular2mcap
Version: 0.1.12
Summary: Convert tabular data (CSV, Parquet, Excel, etc.) to MCAP format with support for ROS2 and JSON schemas
Requires-Python: >=3.10
License-File: LICENSE
Requires-Dist: jinja2>=3.0.0
Requires-Dist: mcap>=1.3.0
Requires-Dist: mcap-ros1-support>=0.7.3
Requires-Dist: mcap-ros2-support>=0.5.5
Requires-Dist: pandas>=2.3.3
Requires-Dist: pydantic>=2.12.0
Requires-Dist: scipy>=1.15.3
Requires-Dist: tqdm>=4.67.1
Requires-Dist: av<16.0.0,>=15.0.0
Requires-Dist: opencv-python>=4.12.0.88
Requires-Dist: platformdirs>=4.5.0
Provides-Extra: parquet
Requires-Dist: pyarrow>=21.0.0; extra == "parquet"
Provides-Extra: feather
Requires-Dist: pyarrow>=21.0.0; extra == "feather"
Provides-Extra: orc
Requires-Dist: pyarrow>=21.0.0; extra == "orc"
Provides-Extra: excel
Requires-Dist: openpyxl>=3.0.0; extra == "excel"
Provides-Extra: excel-legacy
Requires-Dist: xlrd>=2.0.0; extra == "excel-legacy"
Provides-Extra: xml
Requires-Dist: lxml>=4.9.0; extra == "xml"
Provides-Extra: protobuf
Requires-Dist: mcap-protobuf-support>=0.5.2; extra == "protobuf"
Requires-Dist: foxglove-schemas-protobuf>=0.1.1; extra == "protobuf"
Provides-Extra: all-formats
Requires-Dist: pyarrow>=21.0.0; extra == "all-formats"
Requires-Dist: openpyxl>=3.0.0; extra == "all-formats"
Requires-Dist: xlrd>=2.0.0; extra == "all-formats"
Requires-Dist: lxml>=4.9.0; extra == "all-formats"
Dynamic: license-file
